visualkit/__init__.py
visualkit/__main__.py
visualkit/config.py
visualkit/editor.py
visualkit/enums.py
visualkit/media_element.py
visualkit/project_creator.py
visualkit/text_element.py
visualkit/timeline.py
visualkit/transitions.py
visualkit/utils.py
visualkit-0.1.4.dist-info/licenses/AUTHORS.rst
visualkit-0.1.4.dist-info/licenses/LICENSE
visualkit-0.1.4.dist-info/METADATA
visualkit-0.1.4.dist-info/WHEEL
visualkit-0.1.4.dist-info/top_level.txt
visualkit-0.1.4.dist-info/RECORD
