Metadata-Version: 2.4
Name: visualkit
Version: 0.1.4
Summary: Lightning-fast Python package for video frame effects and transitions. Comprehensive collection of visual effects with optimized OpenCV backend for maximum rendering speed.
Author-email: Suraj Airi <surajairi.ml@gmail.com>
License: MIT license
Requires-Python: >=3.9
License-File: LICENSE
License-File: AUTHORS.rst
Requires-Dist: numpy>=2.0.2
Requires-Dist: opencv-python>=4.12.0.88
Dynamic: license-file
